{
 "version": 1,
 "key_columns": [
  "relation_id"
 ],
 "by_key": {
  "85736@18_4-85736@18_8": {
   "is_correct": false
  },
  "58803@18_42-58803@18_15": {
   "is_correct": true
  },
  "130601@26_34-130601@26_21": {
   "is_correct": false
  },
  "133318@46_20-133318@46_33": {
   "is_correct": false
  },
  "38897@10_23-38897@10_20": {
   "is_correct": false
  },
  "82383@26_59-82383@26_8": {
   "is_correct": false
  },
  "72549@33_42-72549@33_15": {
   "is_correct": false
  },
  "154431@2_99-154431@2_156": {
   "is_correct": false
  },
  "154470@22_12-154470@22_8": {
   "is_correct": true
  },
  "71991@58_0-71991@58_7": {
   "is_correct": false
  },
  "25919@39_3-25919@39_6": {
   "is_correct": false
  },
  "14698@41_7-14698@41_28": {
   "is_correct": false
  },
  "45661@0_20-45661@0_41": {
   "is_correct": false
  },
  "10726@13_20-10726@13_24": {
   "is_correct": false
  },
  "103891@38_5-103891@38_23": {
   "is_correct": false
  },
  "90491@2_20-90491@2_22": {
   "is_correct": false
  },
  "25360@59_54-25360@59_48": {
   "is_correct": false
  },
  "90491@18_22-90491@18_24": {
   "is_correct": false
  },
  "3704@4_15-3704@4_18": {
   "is_correct": false
  },
  "86647@28_13-86647@28_21": {
   "is_correct": false
  },
  "103891@38_23-103891@38_54": {
   "is_correct": false
  },
  "56584@15_51-56584@15_71": {
   "is_correct": false
  },
  "139064@43_53-139064@43_23": {
   "is_correct": false
  },
  "42693@33_40-42693@33_29": {
   "is_correct": false
  },
  "148797@53_21-148797@53_43": {
   "is_correct": false
  },
  "60823@33_23-60823@33_19": {
   "is_correct": false
  },
  "34215@40_59-34215@40_71": {
   "is_correct": false
  },
  "94918@15_20-94918@15_27": {
   "is_correct": false
  }
 }
}